{
  "test": "dab_sign_flag",
  "mnemonic": "DAB",
  "exec_result": "HALT",
  "cycle_count": 973,
  "fetch_count": 43,
  "trace": [
    {
      "addr": 514,
      "data": 45056,
      "rw": "R",
      "bw": "W",
      "io": "M"
    },
    {
      "addr": 516,
      "data": 24072,
      "rw": "R",
      "bw": "W",
      "io": "M"
    },
    {
      "addr": 518,
      "data": 192,
      "rw": "R",
      "bw": "W",
      "io": "M"
    },
    {
      "addr": 192,
      "data": 28416,
      "rw": "R",
      "bw": "W",
      "io": "M"
    }
  ]
}